als_archiver_client-1.0.3.dist-info/licenses/LICENSE
archivertools/__init__.py
archivertools/archiver_client.py
archivertools/archiving_policy.py
archivertools/pv.py
archivertools/utils.py
archivertools/services/__init__.py
archivertools/services/data_downloader.py
archivertools/services/data_preprocesser.py
als_archiver_client-1.0.3.dist-info/METADATA
als_archiver_client-1.0.3.dist-info/WHEEL
als_archiver_client-1.0.3.dist-info/top_level.txt
als_archiver_client-1.0.3.dist-info/RECORD
