Metadata-Version: 2.4
Name: als-archiver-client
Version: 1.0.3
Summary: A Python package for interacting with the ALS archiver.
Home-page: https://github.com/andrea-pollastro/als-archiver-client
Author: Andrea Pollastro
Author-email: apollastro@lbl.gov
Keywords: epics,archiver,data-mining,engineering,research,particle-accelerator
Classifier: Programming Language :: Python :: 3
Classifier: Programming Language :: Python :: 3.10
Classifier: Programming Language :: Python :: 3.11
Classifier: License :: OSI Approved :: MIT License
Classifier: Operating System :: OS Independent
Classifier: Topic :: Scientific/Engineering
Classifier: Topic :: Software Development :: Libraries :: Python Modules
Requires-Python: >=3.10
License-File: LICENSE
Requires-Dist: numpy>=1.26.3
Requires-Dist: pandas>=2.1.4
Requires-Dist: python-dateutil>=2.8.2
Requires-Dist: pytz>=2023.3
Requires-Dist: six>=1.16.0
Requires-Dist: tzdata>=2023.3
Requires-Dist: urllib3>=2.0.0
Requires-Dist: tqdm>=4.65.0
Dynamic: author
Dynamic: author-email
Dynamic: classifier
Dynamic: description
Dynamic: description-content-type
Dynamic: home-page
Dynamic: keywords
Dynamic: license-file
Dynamic: requires-dist
Dynamic: requires-python
Dynamic: summary
